libhelp/_init_.py
libhelp/help.py
libhelp-0.0.8.dist-info/METADATA
libhelp-0.0.8.dist-info/WHEEL
libhelp-0.0.8.dist-info/licenses/LICENSE
libhelp-0.0.8.dist-info/RECORD
