Metadata-Version: 2.4
Name: libhelp
Version: 0.0.8
Summary: A Python library helper.
Project-URL: Homepage, https://github.com/webro-13/libhelp
Project-URL: Issues, https://github.com/webro-13/libhelp/issues
Author-email: Rocco S <robotmen13@gmail.com>
License-Expression: MIT
License-File: LICENSE
Classifier: Operating System :: OS Independent
Classifier: Programming Language :: Python :: 3
Requires-Python: >=3.8
